astarRobi/__init__.py
astarRobi-1.0.6.dist-info/LICENSE
astarRobi-1.0.6.dist-info/METADATA
astarRobi-1.0.6.dist-info/WHEEL
astarRobi-1.0.6.dist-info/top_level.txt
astarRobi-1.0.6.dist-info/RECORD
