Metadata-Version: 2.1
Name: astarRobi
Version: 1.0.6
Summary: A package for A* Search Algorithm
Home-page: https://github.com/Mrrobi/astarSearch
Author: Md Robiuddin
Author-email: mrrobi040@hotmail.com
License: UNKNOWN
Platform: UNKNOWN
Classifier: Programming Language :: Python :: 3
Classifier: License :: OSI Approved :: MIT License
Classifier: Operating System :: OS Independent
Requires-Python: >=3.6
